{"status":"success","totalPages":2,"total":3,"pageSize":36,"page":1,"items":[{"id":"4XLFLKGPOI","seriesId":"EYODKAA2ZE","status":"ON_SALE","name":"Eesti Kontserdi kinkepilet","sluggedName":"eesti-kontserdi-kinkepilet","imageData":[{"type":"DESKTOP","imageId":"fe1cab2e-f9c7-4102-a109-a43409e53f42"}],"eventStartAt":"2018-10-25T20:59:00Z","categories":[],"seriesEvents":[],"links":[],"venue":{"name":"Kinkepilet","country":"EE","imageData":[]}},{"id":"JM77KMXFXY","seriesId":"TWZI7N2ST4","status":"ON_SALE","name":"Vaba Lava Kinkepilet","sluggedName":"vaba-lava-kinkepilet","imageData":[{"type":"DESKTOP","imageId":"554b428d-ce00-4b8c-814e-705f6f409e21"}],"eventStartAt":"2018-12-31T10:00:00Z","categories":[],"seriesEvents":[],"links":[],"venue":{"name":"Kinkepilet","country":"EE","imageData":[]}}]}
